{
  "id": "f8b5a872-e644-4fb9-925b-517fc318d31e",
  "prevId": "00000000-0000-0000-0000-000000000000",
  "version": "5",
  "dialect": "pg",
  "tables": {
    "meals": {
      "name": "meals",
      "schema": "",
      "columns": {
        "id": {
          "name": "id",
          "type": "uuid",
          "primaryKey": true,
          "notNull": true,
          "default": "gen_random_uuid()"
        },
        "name": {
          "name": "name",
          "type": "varchar(92)",
          "primaryKey": false,
          "notNull": true
        },
        "description": {
          "name": "description",
          "type": "text",
          "primaryKey": false,
          "notNull": true
        },
        "timestamp": {
          "name": "timestamp",
          "type": "timestamp",
          "primaryKey": false,
          "notNull": true
        },
        "is_on_diet": {
          "name": "is_on_diet",
          "type": "boolean",
          "primaryKey": false,
          "notNull": true
        },
        "user_id": {
          "name": "user_id",
          "type": "uuid",
          "primaryKey": false,
          "notNull": true
        }
      },
      "indexes": {},
      "foreignKeys": {
        "meals_user_id_users_id_fk": {
          "name": "meals_user_id_users_id_fk",
          "tableFrom": "meals",
          "tableTo": "users",
          "columnsFrom": [
            "user_id"
          ],
          "columnsTo": [
            "id"
          ],
          "onDelete": "no action",
          "onUpdate": "no action"
        }
      },
      "compositePrimaryKeys": {},
      "uniqueConstraints": {}
    },
    "users": {
      "name": "users",
      "schema": "",
      "columns": {
        "id": {
          "name": "id",
          "type": "uuid",
          "primaryKey": true,
          "notNull": true,
          "default": "gen_random_uuid()"
        },
        "name": {
          "name": "name",
          "type": "varchar(92)",
          "primaryKey": false,
          "notNull": true
        },
        "email": {
          "name": "email",
          "type": "varchar(256)",
          "primaryKey": false,
          "notNull": true
        },
        "hashed_password": {
          "name": "hashed_password",
          "type": "varchar(72)",
          "primaryKey": false,
          "notNull": true
        }
      },
      "indexes": {},
      "foreignKeys": {},
      "compositePrimaryKeys": {},
      "uniqueConstraints": {
        "users_email_unique": {
          "name": "users_email_unique",
          "nullsNotDistinct": false,
          "columns": [
            "email"
          ]
        }
      }
    }
  },
  "enums": {},
  "schemas": {},
  "_meta": {
    "schemas": {},
    "tables": {},
    "columns": {}
  }
}